LICENSE
MANIFEST.in
README.md
setup.py
notdb_cloud/__init__.py
notdb_cloud/__main__.py
notdb_cloud.egg-info/PKG-INFO
notdb_cloud.egg-info/SOURCES.txt
notdb_cloud.egg-info/dependency_links.txt
notdb_cloud.egg-info/entry_points.txt
notdb_cloud.egg-info/not-zip-safe
notdb_cloud.egg-info/requires.txt
notdb_cloud.egg-info/top_level.txt
notdb_cloud/app/__init__.py
notdb_cloud/app/templates/get_password.html
notdb_cloud/app/templates/index.html
notdb_cloud/app/templates/viewer.html