Metadata-Version: 2.1
Name: notdb-cloud
Version: 1.0.1
Summary: An API to send or get data from NotDB databases on cloud
Home-page: https://github.com/nawafalqari/NotDB_Cloud/
Author: Nawaf Alqari
Author-email: nawafalqari13@gmail.com
License: MIT
Project-URL: Documentation, https://github.com/nawafalqari/NotDB_Cloud#readme
Project-URL: Bug Tracker, https://github.com/nawafalqari/NotDB_Cloud/issues
Project-URL: Source Code, https://github.com/nawafalqari/NotDB_Cloud/
Project-URL: Discord, https://discord.gg/cpvynqk4XT
Project-URL: Donate, https://paypal.me/NawafHAlqari
Keywords: notdb,db,database,notdatabsae,simple database
Platform: UNKNOWN
Classifier: Programming Language :: Python :: 3
Classifier: License :: OSI Approved :: MIT License
Classifier: Operating System :: OS Independent
Classifier: Topic :: Database
License-File: LICENSE
